[
  {
    "name": "theme_info",
    "theme_name": "Rubato",
    "theme_version": "1.0.0",
    "theme_author": "Björn Berglund",
    "theme_documentation_url": "https:\/\/help.shopify.com\/manual\/online-store\/themes\/os20\/themes-by-shopify\/dawn",
    "theme_support_url": "https:\/\/support.shopify.com\/"
  },
  {
    "name": "DDP Banner",
    "settings": [
      {
        "id": "text",
        "type": "textarea",
        "label": "Text"
      },
      {
        "type": "header",
        "content": "Countries"
      },
      {
        "type": "checkbox",
        "id": "ddp_SE",
        "label": "Sweden",
        "default": false
      }
    ]
  }
]
